leaf/application.py
leaf/infrastructure.py
leaf/orchestrator.py
leaf/power.py
leafsim-0.1.2.dist-info/LICENSE
leafsim-0.1.2.dist-info/WHEEL
leafsim-0.1.2.dist-info/METADATA
leafsim-0.1.2.dist-info/RECORD
