Metadata-Version: 2.1
Name: leafsim
Version: 0.1.2
Summary: A simulator for Large Energy-Aware Fog computing environments.
Home-page: https://github.com/dos-group/leaf
License: MIT
Keywords: simulation,modeling,fog computing,energy consumption,edge computing
Author: Philipp Wiesner
Author-email: wiesner@tu-berlin.de
Requires-Python: >=3.7.9,<4.0.0
Classifier: Development Status :: 3 - Alpha
Classifier: Intended Audience :: Education
Classifier: Intended Audience :: Science/Research
Classifier: License :: OSI Approved :: MIT License
Classifier: Operating System :: OS Independent
Classifier: Programming Language :: Python
Classifier: Programming Language :: Python :: 3
Classifier: Programming Language :: Python :: 3.6
Classifier: Programming Language :: Python :: 3.7
Classifier: Programming Language :: Python :: 3.8
Classifier: Programming Language :: Python :: 3.9
Classifier: Topic :: Education
Classifier: Topic :: Scientific/Engineering
Classifier: Topic :: Scientific/Engineering :: Information Analysis
Classifier: Topic :: Software Development :: Libraries :: Python Modules
Classifier: Topic :: System :: Distributed Computing
Classifier: Typing :: Typed
Provides-Extra: docs
Requires-Dist: networkx (>=2.5,<3.0)
Requires-Dist: numpy (>=1.20.0,<2.0.0)
Requires-Dist: pandas (>=1.2.1,<2.0.0)
Requires-Dist: simpy (>=4.0.0,<5.0.0)
Requires-Dist: tqdm (>=4.0.0,<5.0.0)
Project-URL: Documentation, https://leaf.readthedocs.io
Project-URL: Repository, https://github.com/dos-group/leaf
